aggin/__init__.py
aggin/aggin.py
aggin/shell.py
aggin/strings_with_arrows.py
AggiNScript-0.3.dist-info/METADATA
AggiNScript-0.3.dist-info/WHEEL
AggiNScript-0.3.dist-info/entry_points.txt
AggiNScript-0.3.dist-info/top_level.txt
AggiNScript-0.3.dist-info/RECORD
