Metadata-Version: 2.1
Name: AggiNScript
Version: 0.3
Summary: My Custom Programming Language
Author: Aman
